setup.py
restorepoint/__init__.py
restorepoint/restorepoint.py
restorepoint/rp.py
restorepoint.egg-info/PKG-INFO
restorepoint.egg-info/SOURCES.txt
restorepoint.egg-info/dependency_links.txt
restorepoint.egg-info/entry_points.txt
restorepoint.egg-info/requires.txt
restorepoint.egg-info/top_level.txt