Metadata-Version: 1.0
Name: restorepoint
Version: 1.1.0
Summary: Python API wrapper for RestorePoint
Home-page: https://github.com/pschmitt/python-restorepoint
Author: Philipp Schmitt
Author-email: philipp@schmitt.co
License: GPL3
Platform: UNKNOWN
